AUTHORS.rst
CONTRIBUTING.rst
HISTORY.rst
LICENSE
MANIFEST.in
README.md
pyproject.toml
setup.cfg
src/cosmic_toolbox/MultiInterp.py
src/cosmic_toolbox/NearestWeightedNDInterpolator.py
src/cosmic_toolbox/TransformedGaussianMixture.py
src/cosmic_toolbox/__init__.py
src/cosmic_toolbox/arraytools.py
src/cosmic_toolbox/colors.py
src/cosmic_toolbox/copy_guardian.py
src/cosmic_toolbox/file_utils.py
src/cosmic_toolbox/logger.py
src/cosmic_toolbox/utils.py
src/cosmic_toolbox.egg-info/PKG-INFO
src/cosmic_toolbox.egg-info/SOURCES.txt
src/cosmic_toolbox.egg-info/dependency_links.txt
src/cosmic_toolbox.egg-info/not-zip-safe
src/cosmic_toolbox.egg-info/requires.txt
src/cosmic_toolbox.egg-info/top_level.txt
tests/test_arraytools.py
tests/test_cosmic_toolbox.py
tests/test_file_utils.py
tests/test_logger.py
tests/test_utils.py