Metadata-Version: 2.1
Name: cosmic-toolbox
Version: 0.5.1
Summary: Collection of code from the Cosmology Research Group at ETH
Author: Silvan Fischbacher
Author-email: silvanf@phys.ethz.ch
License: MIT License
Project-URL: Source, https://cosmo-docs.phys.ethz.ch/cosmic_toolbox
Platform: UNKNOWN
Classifier: Intended Audience :: Science/Research
Classifier: Intended Audience :: Developers
Classifier: License :: OSI Approved :: MIT License
Classifier: Natural Language :: English
Classifier: Programming Language :: Python :: 3
Classifier: Programming Language :: Python :: 3.10
Classifier: Programming Language :: Python :: 3.11
Classifier: Programming Language :: Python :: 3.12
Classifier: Programming Language :: Python :: 3.13
Classifier: Operating System :: OS Independent
Requires-Python: >=3.7
Provides-Extra: dev
Provides-Extra: docs
License-File: LICENSE
License-File: AUTHORS.rst
